polymorphic/tools_for_tests.py
polymorphic/models.py
polymorphic/query.py
polymorphic/__version__.py
polymorphic/__init__.py
polymorphic/manager.py
polymorphic/query_translate.py
polymorphic/admin.py
polymorphic/tests.py
polymorphic/base.py
polymorphic/showfields.py
polymorphic/templates/admin/polymorphic/change_form.html
polymorphic/templates/admin/polymorphic/add_type_form.html
polymorphic/templates/admin/polymorphic/delete_confirmation.html
polymorphic/templatetags/polymorphic_admin_tags.py
polymorphic/templatetags/__init__.py
django_polymorphic_ng-0.8.0.dist-info/top_level.txt
django_polymorphic_ng-0.8.0.dist-info/RECORD
django_polymorphic_ng-0.8.0.dist-info/metadata.json
django_polymorphic_ng-0.8.0.dist-info/WHEEL
django_polymorphic_ng-0.8.0.dist-info/DESCRIPTION.rst
django_polymorphic_ng-0.8.0.dist-info/METADATA
