Metadata-Version: 2.0
Name: django-polymorphic-ng
Version: 0.8.0
Summary: Seamless Polymorphic Inheritance for Django Models
Home-page: https://github.com/chrisglass/django_polymorphic
Author: Christopher Glass
Author-email: tribaal@gmail.com
License: BSD
Platform: UNKNOWN
Classifier: Development Status :: 5 - Production/Stable
Classifier: Framework :: Django
Classifier: Intended Audience :: Developers
Classifier: License :: OSI Approved :: BSD License
Classifier: Operating System :: OS Independent
Classifier: Programming Language :: Python
Classifier: Programming Language :: Python :: 2.6
Classifier: Programming Language :: Python :: 2.7
Classifier: Programming Language :: Python :: 3.3
Classifier: Framework :: Django
Classifier: Framework :: Django :: 1.4
Classifier: Framework :: Django :: 1.5
Classifier: Framework :: Django :: 1.6
Classifier: Framework :: Django :: 1.7
Classifier: Framework :: Django :: 1.8
Classifier: Topic :: Software Development :: Libraries :: Python Modules
